[
    {"x": 15.6, "y": 23.8},
    {"x": 7.2, "y": 10.9},
    {"x": 32.1, "y": 45.6},
    {"x": 18.9, "y": 37.4},
    {"x": 5.3, "y": 29.0},
    {"x": 41.2, "y": 12.6},
    {"x": 27.8, "y": 8.9},
    {"x": 14.0, "y": 19.7},
    {"x": 35.5, "y": 30.2},
    {"x": 9.6, "y": 47.1},
    {"x": 25.3, "y": 38.5},
    {"x": 48.7, "y": 16.4},
    {"x": 31.2, "y": 22.7},
    {"x": 20.4, "y": 5.8},
    {"x": 3.9, "y": 43.2},
    {"x": 12.8, "y": 31.5},
    {"x": 38.6, "y": 20.1},
    {"x": 29.0, "y": 9.4},
    {"x": 17.5, "y": 40.7},
    {"x": 6.7, "y": 14.8},
    {"x": 22.3, "y": 33.6},
    {"x": 40.9, "y": 26.7},
    {"x": 10.1, "y": 2.4},
    {"x": 27.4, "y": 18.3},
    {"x": 34.8, "y": 36.9},
    {"x": 16.2, "y": 48.5},
    {"x": 21.5, "y": 7.1},
    {"x": 5.9, "y": 39.4},
    {"x": 37.3, "y": 29.8},
    {"x": 11.4, "y": 25.6}
]